lumispy/__init__.py
lumispy/hyperspy_extension.yaml
lumispy/components/__init__.py
lumispy/signals/__init__.py
lumispy/signals/cl_spectrum.py
lumispy/signals/common_luminescence.py
lumispy/signals/common_transient.py
lumispy/signals/el_spectrum.py
lumispy/signals/luminescence_spectrum.py
lumispy/signals/luminescence_transient.py
lumispy/signals/luminescence_transientspec.py
lumispy/signals/pl_spectrum.py
lumispy/tests/__init__.py
lumispy/tests/test_signal_registration.py
lumispy/tests/signals/__init__.py
lumispy/tests/signals/test_cl_sem_spectrum.py
lumispy/tests/signals/test_cl_spectrum.py
lumispy/tests/signals/test_common_luminescence.py
lumispy/tests/signals/test_luminescence_spectrum.py
lumispy/tests/signals/test_luminescence_transient_spectrum.py
lumispy/tests/utils/__init__.py
lumispy/tests/utils/test_axis_conversion.py
lumispy/tests/utils/test_io.py
lumispy/tests/utils/test_joinspectra.py
lumispy/tests/utils/test_signals.py
lumispy/utils/__init__.py
lumispy/utils/axes.py
lumispy/utils/io.py
lumispy/utils/signals.py
lumispy-0.3.0.dist-info/LICENSE
lumispy-0.3.0.dist-info/METADATA
lumispy-0.3.0.dist-info/WHEEL
lumispy-0.3.0.dist-info/entry_points.txt
lumispy-0.3.0.dist-info/top_level.txt
lumispy-0.3.0.dist-info/RECORD
