Metadata-Version: 2.2
Name: lumispy
Version: 0.3.0
Summary: Analysis of luminescence spectroscopy data with HyperSpy.
Author: The LumiSpy developers
License:                     GNU GENERAL PUBLIC LICENSE
Project-URL: Bug Reports, https://github.com/lumispy/lumispy/issues
Project-URL: Conda-forge, https://anaconda.org/conda-forge/lumispy
Project-URL: Documentation, https://docs.lumispy.org
Project-URL: Homepage, https://lumispy.org
Project-URL: Source, https://github.com/lumispy/lumispy
Keywords: CL,PL,EL,TRCL,TRPL,SEM,STEM,TEM,cathodoluminescence,photoluminescence,electroluminescence,Raman,curve fitting,data analysis,electron microscopy,hyperspectral,hyperspectrum,hyperspy,luminescence spectroscopy,lumispy,machine learning,model,multidimensional,numpy,python,scipy,spectroscopy,spectrum image,time-resolved
Classifier: Development Status :: 4 - Beta
Classifier: Intended Audience :: Developers
Classifier: Intended Audience :: Science/Research
Classifier: License :: OSI Approved :: GNU General Public License v3 (GPLv3)
Classifier: Natural Language :: English
Classifier: Operating System :: OS Independent
Classifier: Programming Language :: Python :: 3.9
Classifier: Programming Language :: Python :: 3.10
Classifier: Programming Language :: Python :: 3.11
Classifier: Programming Language :: Python :: 3.12
Classifier: Programming Language :: Python :: 3.13
Classifier: Topic :: Scientific/Engineering
Classifier: Topic :: Scientific/Engineering :: Physics
Classifier: Topic :: Software Development :: Libraries
Requires-Python: >=3.9
License-File: LICENSE
Requires-Dist: hyperspy>=1.7.3
Requires-Dist: numpy
Requires-Dist: scipy
Requires-Dist: pint>=0.10
Provides-Extra: tests
Requires-Dist: codecov; extra == "tests"
Requires-Dist: pytest>=5.0; extra == "tests"
Requires-Dist: pytest-cov; extra == "tests"
Requires-Dist: setuptools-scm; extra == "tests"
Requires-Dist: numba; extra == "tests"
Provides-Extra: doc
Requires-Dist: sphinx>=4.3.0; extra == "doc"
Requires-Dist: sphinx_rtd_theme>=0.5.1; extra == "doc"
Requires-Dist: sphinx-copybutton; extra == "doc"
Requires-Dist: sphinxcontrib-towncrier>=0.3.0a0; extra == "doc"
Requires-Dist: towncrier<24; extra == "doc"
Requires-Dist: numba; extra == "doc"
Provides-Extra: dev
Requires-Dist: black; extra == "dev"
Requires-Dist: lumispy[doc]; extra == "dev"
Requires-Dist: lumispy[tests]; extra == "dev"
